app_launcher_mcp/__init__.py
app_launcher_mcp/activator.py
app_launcher_mcp/activator_old.py
app_launcher_mcp/activator_old_backup.py
app_launcher_mcp/apps.py
app_launcher_mcp/mcp-apps.example.json
app_launcher_mcp/server.py
app_launcher_mcp/service.py
fastmcp_app_launcher_test-0.3.3.dist-info/licenses/LICENSE
fastmcp_app_launcher_test-0.3.3.dist-info/METADATA
fastmcp_app_launcher_test-0.3.3.dist-info/WHEEL
fastmcp_app_launcher_test-0.3.3.dist-info/entry_points.txt
fastmcp_app_launcher_test-0.3.3.dist-info/top_level.txt
fastmcp_app_launcher_test-0.3.3.dist-info/RECORD
