Metadata-Version: 2.4
Name: fastmcp-app-launcher-test
Version: 0.3.3
Summary: 基于 fastmcp 的跨平台应用启动 MCP 服务
Author-email: Codex MCP <codex@example.com>
License: MIT License
Project-URL: Homepage, https://github.com/fjc/fastmcp-app-launcher
Project-URL: Repository, https://github.com/fjc/fastmcp-app-launcher
Project-URL: Bug Tracker, https://github.com/fjc/fastmcp-app-launcher/issues
Keywords: mcp,fastmcp,automation,launcher,productivity
Classifier: Development Status :: 4 - Beta
Classifier: Intended Audience :: Developers
Classifier: License :: OSI Approved :: MIT License
Classifier: Programming Language :: Python :: 3
Classifier: Programming Language :: Python :: 3.10
Classifier: Programming Language :: Python :: 3.11
Classifier: Programming Language :: Python :: 3.12
Classifier: Operating System :: OS Independent
Classifier: Topic :: Desktop Environment
Classifier: Topic :: System :: Monitoring
Requires-Python: >=3.10
License-File: LICENSE
Requires-Dist: fastmcp>=2.12.0
Requires-Dist: pydantic>=2.9.0
Requires-Dist: pywin32>=305; sys_platform == "win32"
Requires-Dist: pywinauto>=0.6.8; sys_platform == "win32"
Requires-Dist: psutil>=5.9.0; sys_platform == "win32"
Provides-Extra: windows
Requires-Dist: pywin32>=305; extra == "windows"
Requires-Dist: pywinauto>=0.6.8; extra == "windows"
Requires-Dist: psutil>=5.9.0; extra == "windows"
Provides-Extra: dev
Requires-Dist: pytest>=8.3.0; extra == "dev"
Requires-Dist: pytest-asyncio>=0.23.0; extra == "dev"
Dynamic: license-file
